mcp_json_to_csv/__init__.py
mcp_json_to_csv/server.py
mcp_json_to_csv-0.0.1.dist-info/METADATA
mcp_json_to_csv-0.0.1.dist-info/WHEEL
mcp_json_to_csv-0.0.1.dist-info/entry_points.txt
mcp_json_to_csv-0.0.1.dist-info/licenses/LICENSE
mcp_json_to_csv-0.0.1.dist-info/licenses/NOTICE
mcp_json_to_csv-0.0.1.dist-info/RECORD
