Metadata-Version: 2.4
Name: mcp-json-to-csv
Version: 0.0.1
Summary: MCP Server for JSON to CSV convertion.
Author: AI/Run Team
Maintainer: AI/Run Team
License: MIT
License-File: LICENSE
License-File: NOTICE
Keywords: convertion,csv,json,mcp
Requires-Python: >=3.10
Requires-Dist: mcp>=1.0.0
Requires-Dist: mcp[cli]>=1.9.2
Requires-Dist: pydantic>=2.0.0
